[
  {
    "name": "Сырники из творога",
    "cookingTime": "30 минут",
    "ingredients": [
      {
        "nameI": "Творог ",
        "countI": 350,
        "unitsOfMeasurement": "г."

      },
      {
        "nameI": "Куриное яйцо",
        "countI": 2,
        "unitsOfMeasurement": "шт."

      },
      {
        "nameI": "Пшеничная мука",
        "countI": 6,
        "unitsOfMeasurement": "ст.л."

      },
      {
        "nameI": "Сахар",
        "countI": 2,
        "unitsOfMeasurement": "ст.л."

      }

    ],
    "instructions": {
      "steps": {
        "1": "Смешайте весь творог с яйцами, сахаром и тщательно всё перемешайте.",
        "2":"Всыпьте, в творог муку и тщательно перемешайте.",
        "3":"Поставьте, сковороду на средний огонь и налейте в нее подсолнечное масло.",
        "4":"Слепите, несколько небольших шариков из получившейся творожной массы и положите их на тарелку.",
        "5":"Затем по очереди обкатывайте творожные шарики в муке и выкладывайте на сковороду.",
        "6":"Обжаривайте, сырники 1–2 минуты до появления золотистой корочки,",
        "7":"Затем переверните их на другую сторону и также обжарьте до золотистого состояния.",
        "8":"Повторяйте,пока творог не закончится."
      }
    }

  },
  {
    "name": "Салат из красной фасоли с творожным сыром, красным луком и сезонным салатом",
    "cookingTime": "7 минут",
    "ingredients": [
      {
        "nameI": "Специи",
        "countI": 0,
        "unitsOfMeasurement": "по вкусу"
      },
      {
        "nameI": "Консервированная фасоль",
        "countI": 400,
        "unitsOfMeasurement": "г."
      },
      {
        "nameI": "Лимон",
        "countI": 1,
        "unitsOfMeasurement": "шт."

      },
      {
        "nameI": "Чеснок",
        "countI": 2,
        "unitsOfMeasurement": "зуб."
      },
{
        "nameI": "Оливковое масло",
        "countI": 50,
        "unitsOfMeasurement": "мл."
      },
{
        "nameI": "Рукола",
        "countI": 100,
        "unitsOfMeasurement": "г."
      },
      {
        "nameI": "Творожный сыр",
        "countI": 200,
        "unitsOfMeasurement": "г."
      },
      {
        "nameI": "Красный лук",
        "countI": 50,
        "unitsOfMeasurement": "г."
      }

    ],
    "instructions": {
      "steps": {
        "1":"Открыть две банки красной фасоли в собственном соку.",
        "2":"Слить сок и промыть фасоль холодной водой.",
        "3":"Готовую фасоль смешать с мелко нарубленным красным луком, зеленью, давленым чесноком, оливковым маслом, лимонным соком и творожным сыром.",
        "4":"Посолить.",
        "5":"Поперчить.",
        "6":"дать продуктам две минуты притереться друг к другу.",
        "7":"Подавать к столу.",
        "8":null
      }
    }

  },
  {
    "name": "Чечевичный суп с мятой",
    "cookingTime": "30 минут",
    "ingredients": [
      {
        "nameI": "Специи",
        "countI": 0,
        "unitsOfMeasurement": "по вкусу"
      },
      {"nameI": "Мята",
        "countI": 0,
        "unitsOfMeasurement": "по вкусу"
      },
      {
        "nameI": "Консервированная фасоль",
        "countI": 400,
        "unitsOfMeasurement": "г."
      },
      {
        "nameI": "Лимон",
        "countI": 0.5,
        "unitsOfMeasurement": "шт."

      },
      {
        "nameI": "Сливки 33%",
        "countI": 50,
        "unitsOfMeasurement": "мл."
      },
      {
        "nameI": "Подсолнечное масло",
        "countI": 30,
        "unitsOfMeasurement": "мл."
      },
      {
        "nameI": "Сливочное масло",
        "countI": 15,
        "unitsOfMeasurement": "г."
      },
      {
        "nameI": "Репчатый лук",
        "countI": 1,
        "unitsOfMeasurement": "гол."
      },
      {
        "nameI": "Красная чечевица",
        "countI": 150,
        "unitsOfMeasurement": "г."
      },
      {
        "nameI": "Морковь",
        "countI": 1,
        "unitsOfMeasurement": "шт."
      },
      {
        "nameI": "Пшеничная мука",
        "countI": 30,
        "unitsOfMeasurement": "г."
      }

    ],
    "instructions": {
      "steps": {
        "1":"В небольшую кастрюлю налить литр воды и засыпать промытую чечевицу.",
        "2":"Поставить кастрюлю на средний огонь.",
        "3":"Натереть небольшую морковь на крупной терке, мелко нарезать лук.",
        "4":"Как только чечевица начнет кипеть, надо убавить огонь.",
        "5":"Затем долить еще 200 мл воды или бульона, варить еще десять минут.",
        "6":"Разогреть широкую плоскую сковороду, добавить туда подсолнечное и сливочное масло.",
        "7":"Обжарить лук и морковь. Добавить обжаренные овощи в кастрюлю, влить сливки.",
        "8":"Взбить суп ручным блендером, чтобы он превратился в густое пюре, подать к столу"
      }
    }

  },
  {
    "name": "Салат с креветками и кунжутом",
    "cookingTime": "20 минут",
    "ingredients": [
      {
        "nameI": "Помидоры",
        "countI": 3,
        "unitsOfMeasurement": "шт."
      },
      {
        "nameI": "Королевские креветки",
        "countI": 300,
        "unitsOfMeasurement": "г."
      },
      {
        "nameI": "Зеленый салат",
        "countI": 1,
        "unitsOfMeasurement": "пучок"

      },
      {
        "nameI": "Огурцы",
        "countI": 2,
        "unitsOfMeasurement": "шт."
      },
      {
        "nameI": "Специи",
        "countI": 0,
        "unitsOfMeasurement": "по вкусу"
      },
      {
        "nameI": "Майонез",
        "countI": 0,
        "unitsOfMeasurement": "по вкусу"
      },
      {
        "nameI": "Кунжутные семечки",
        "countI": 3,
        "unitsOfMeasurement": "ст.л."
      }

    ],
    "instructions": {
      "steps": {
        "1":"Порезать овощи крупно.",
        "2":"Салат порвать на куски.",
        "3":"Довести до кипения сильно соленую воду и добавить креветки.",
        "4":"Очистить креветки от панциря.",
        "5":"Смешать овощи и креветки.",
        "6":"Посыпать кунжутными семечками и заправить майонезом.",
        "7":"Подавать к столу.",
        "8":null
      }
    }

  },
  {
    "name": "Творожные пончики в сахарной пудре",
    "cookingTime": "40 минут",
    "ingredients": [
      {
        "nameI": "Творог",
        "countI": 250,
        "unitsOfMeasurement": "г."
      },
      {
        "nameI": "Куриное яйцо",
        "countI": 3,
        "unitsOfMeasurement": "шт."
      },
      {
        "nameI": "Пшеничная мука",
        "countI": 8,
        "unitsOfMeasurement": "ст.л."

      },
      {
        "nameI": "Оливковое масло",
        "countI": 0,
        "unitsOfMeasurement": "по вкусу"
      },
      {
        "nameI": "Сахар и соль",
        "countI": 0,
        "unitsOfMeasurement": "по вкусу"
      },
      {
        "nameI": "Сода",
        "countI": 0.5,
        "unitsOfMeasurement": "ст.л"
      },
      {
        "nameI": "Сахарная пудра с ванилью",
        "countI": 0,
        "unitsOfMeasurement": "по вкусу"
      }

    ],
    "instructions": {
      "steps": {
        "1":"В миске смешать творог, яйца, муку, сахар, соду и соль до однородной консистенции.",
        "2":"В небольшом сотейнике оливковое масло хорошо разогреть.",
        "3":"При помощи чайной ложки или руками скатать из теста шарики, каждый размером чуть меньше грецкого ореха.",
        "4":"Бросить пончики в кипящее масло и жарить на небольшом огне, постоянно переворачивая шумовкой.",
        "5":"Готовые пончики выложить на бумажное полотенце и оставить на одну-две минуты — чтобы оно впитало лишнее масло.",
        "6":" Подавать пончики горячими, выложив на блюдо и посыпав сахарной пудрой, смешанной с ванилином.",
        "7":null,
        "8":null
      }
    }

  }
]